randombetter/__init__.py
randombetter/randomness.py
randombetter-1.0.3.1.dist-info/METADATA
randombetter-1.0.3.1.dist-info/WHEEL
randombetter-1.0.3.1.dist-info/top_level.txt
randombetter-1.0.3.1.dist-info/RECORD
