Metadata-Version: 2.1
Name: randombetter
Version: 1.0.3.1
Summary: a slowly developing randomness package
Author: Marek
Author-email: marekciganik0603@gmail.com
Classifier: Programming Language :: Python :: 3
Classifier: License :: OSI Approved :: MIT License
Classifier: Operating System :: OS Independent
Requires-Python: >=3.6
